bumpreqs/__init__.py
bumpreqs/__main__.py
bumpreqs/cli.py
bumpreqs/core.py
bumpreqs/marker_extract.py
bumpreqs/vrange.py
bumpreqs-0.9.3.dist-info/LICENSE
bumpreqs-0.9.3.dist-info/METADATA
bumpreqs-0.9.3.dist-info/WHEEL
bumpreqs-0.9.3.dist-info/entry_points.txt
bumpreqs-0.9.3.dist-info/top_level.txt
bumpreqs-0.9.3.dist-info/RECORD
