Metadata-Version: 2.1
Name: bumpreqs
Version: 0.9.3
Summary: Update requirements to latest
Home-page: https://github.com/python-packaging/bumpreqs/
Author: Tim Hatch
Author-email: tim@timhatch.com
License: MIT
Requires-Python: >=3.8
License-File: LICENSE
Requires-Dist: requests
Requires-Dist: packaging
Requires-Dist: click
Requires-Dist: moreorless
